LICENSE
MANIFEST.in
README.md
setup.py
sentry_sdk/__init__.py
sentry_sdk/_compat.py
sentry_sdk/_functools.py
sentry_sdk/_queue.py
sentry_sdk/_types.py
sentry_sdk/api.py
sentry_sdk/attachments.py
sentry_sdk/client.py
sentry_sdk/consts.py
sentry_sdk/debug.py
sentry_sdk/envelope.py
sentry_sdk/hub.py
sentry_sdk/py.typed
sentry_sdk/scope.py
sentry_sdk/serializer.py
sentry_sdk/session.py
sentry_sdk/sessions.py
sentry_sdk/tracing.py
sentry_sdk/transport.py
sentry_sdk/utils.py
sentry_sdk/worker.py
sentry_sdk/integrations/__init__.py
sentry_sdk/integrations/_wsgi_common.py
sentry_sdk/integrations/aiohttp.py
sentry_sdk/integrations/argv.py
sentry_sdk/integrations/asgi.py
sentry_sdk/integrations/atexit.py
sentry_sdk/integrations/aws_lambda.py
sentry_sdk/integrations/beam.py
sentry_sdk/integrations/boto3.py
sentry_sdk/integrations/bottle.py
sentry_sdk/integrations/celery.py
sentry_sdk/integrations/chalice.py
sentry_sdk/integrations/dedupe.py
sentry_sdk/integrations/excepthook.py
sentry_sdk/integrations/executing.py
sentry_sdk/integrations/falcon.py
sentry_sdk/integrations/flask.py
sentry_sdk/integrations/gcp.py
sentry_sdk/integrations/gnu_backtrace.py
sentry_sdk/integrations/logging.py
sentry_sdk/integrations/modules.py
sentry_sdk/integrations/pure_eval.py
sentry_sdk/integrations/pyramid.py
sentry_sdk/integrations/redis.py
sentry_sdk/integrations/rq.py
sentry_sdk/integrations/sanic.py
sentry_sdk/integrations/serverless.py
sentry_sdk/integrations/sqlalchemy.py
sentry_sdk/integrations/stdlib.py
sentry_sdk/integrations/threading.py
sentry_sdk/integrations/tornado.py
sentry_sdk/integrations/trytond.py
sentry_sdk/integrations/wsgi.py
sentry_sdk/integrations/django/__init__.py
sentry_sdk/integrations/django/asgi.py
sentry_sdk/integrations/django/middleware.py
sentry_sdk/integrations/django/templates.py
sentry_sdk/integrations/django/transactions.py
sentry_sdk/integrations/django/views.py
sentry_sdk/integrations/spark/__init__.py
sentry_sdk/integrations/spark/spark_driver.py
sentry_sdk_custom.egg-info/PKG-INFO
sentry_sdk_custom.egg-info/SOURCES.txt
sentry_sdk_custom.egg-info/dependency_links.txt
sentry_sdk_custom.egg-info/not-zip-safe
sentry_sdk_custom.egg-info/requires.txt
sentry_sdk_custom.egg-info/top_level.txt