Metadata-Version: 2.1
Name: sentry-sdk-custom
Version: 1.1.0
Summary: Python client for Sentry (https://sentry.io)
Home-page: https://github.com/getsentry/sentry-python
Author: Sentry Team and Contributors
Author-email: hello@sentry.io
License: BSD
Project-URL: Documentation, https://docs.sentry.io/platforms/python/
Project-URL: Changelog, https://github.com/getsentry/sentry-python/blob/master/CHANGELOG.md
Platform: UNKNOWN
Classifier: Development Status :: 5 - Production/Stable
Classifier: Environment :: Web Environment
Classifier: Intended Audience :: Developers
Classifier: License :: OSI Approved :: BSD License
Classifier: Operating System :: OS Independent
Classifier: Programming Language :: Python
Classifier: Programming Language :: Python :: 2
Classifier: Programming Language :: Python :: 2.7
Classifier: Programming Language :: Python :: 3
Classifier: Programming Language :: Python :: 3.4
Classifier: Programming Language :: Python :: 3.5
Classifier: Programming Language :: Python :: 3.6
Classifier: Programming Language :: Python :: 3.7
Classifier: Programming Language :: Python :: 3.8
Classifier: Programming Language :: Python :: 3.9
Classifier: Topic :: Software Development :: Libraries :: Python Modules
Provides-Extra: flask
Provides-Extra: bottle
Provides-Extra: falcon
Provides-Extra: django
Provides-Extra: sanic
Provides-Extra: celery
Provides-Extra: beam
Provides-Extra: rq
Provides-Extra: aiohttp
Provides-Extra: tornado
Provides-Extra: sqlalchemy
Provides-Extra: pyspark
Provides-Extra: pure_eval
Provides-Extra: chalice
